mopidy_bandcamp/__init__.py
mopidy_bandcamp/backend.py
mopidy_bandcamp/bandcamp.py
mopidy_bandcamp/ext.conf
mopidy_bandcamp/library.py
mopidy_bandcamp/web.py
Mopidy_Bandcamp-1.1.5.dist-info/LICENSE
Mopidy_Bandcamp-1.1.5.dist-info/METADATA
Mopidy_Bandcamp-1.1.5.dist-info/WHEEL
Mopidy_Bandcamp-1.1.5.dist-info/entry_points.txt
Mopidy_Bandcamp-1.1.5.dist-info/top_level.txt
Mopidy_Bandcamp-1.1.5.dist-info/RECORD
