Metadata-Version: 2.1
Name: Mopidy-Bandcamp
Version: 1.1.5
Summary: Backend for listening to bandcamp
Home-page: https://github.com/impliedchaos/mopidy-bandcamp
Author: Dave Maez
Author-email: impliedchaos@gmail.com
License: MIT License
Platform: UNKNOWN
Classifier: Environment :: No Input/Output (Daemon)
Classifier: Intended Audience :: End Users/Desktop
Classifier: License :: OSI Approved :: MIT License
Classifier: Operating System :: OS Independent
Classifier: Programming Language :: Python :: 3
Classifier: Programming Language :: Python :: 3.7
Classifier: Programming Language :: Python :: 3.8
Classifier: Programming Language :: Python :: 3.9
Classifier: Topic :: Multimedia :: Sound/Audio :: Players
Requires-Dist: setuptools
Requires-Dist: Mopidy (>=3.0.0)
Requires-Dist: Pykka (>=1.1)
